[
  {
    "id": "e796c39d-d1bf-424d-a178-4e9d323693e9",
    "name": "Dave",
    "age": 43,
    "createdAt": "2025-07-22T02:56:46.455Z",
    "score": 18.26,
    "active": false
  },
  {
    "id": "a3efde67-42db-4524-98d8-2b6496382503",
    "name": "Eve",
    "age": 73,
    "createdAt": "2025-07-22T02:56:46.463Z",
    "score": 82.92,
    "active": false
  },
  {
    "id": "27904eda-7331-4f87-9609-23ed356524a1",
    "name": "Eve",
    "age": 50,
    "createdAt": "2025-07-22T02:56:46.482Z",
    "score": 26.29,
    "active": false
  },
  {
    "id": "db7e29c1-c693-4b1e-b36f-0615483f74f3",
    "name": "Carol",
    "age": 36,
    "createdAt": "2025-07-22T02:56:46.489Z",
    "score": 15.9,
    "active": false
  },
  {
    "id": "e085ce8e-4add-49d5-beef-648c20a69ed3",
    "name": "Bob",
    "age": 24,
    "createdAt": "2025-07-22T02:56:46.490Z",
    "score": 45.64,
    "active": true
  },
  {
    "id": "8f7a0c1d-2024-42b3-9886-2b4bb3ee2951",
    "name": "Alice",
    "age": 18,
    "createdAt": "2025-07-22T02:56:46.494Z",
    "score": 44.55,
    "active": true
  },
  {
    "id": "19d0b5a4-86f3-4e35-a423-5807d822f9f8",
    "name": "Eve",
    "age": 40,
    "createdAt": "2025-07-22T02:56:46.498Z",
    "score": 9.64,
    "active": false
  },
  {
    "id": "200d915d-aa9a-469e-b162-9ce0970df011",
    "name": "Frank",
    "age": 51,
    "createdAt": "2025-07-22T02:56:46.503Z",
    "score": 54.71,
    "active": false
  },
  {
    "id": "57579744-4d1e-4485-8507-5375bf705098",
    "name": "Dave",
    "age": 56,
    "createdAt": "2025-07-22T02:56:46.509Z",
    "score": 12.88,
    "active": true
  },
  {
    "id": "0c129460-c687-4f1b-bda4-58f283dab5b4",
    "name": "Carol",
    "age": 73,
    "createdAt": "2025-07-22T02:56:46.515Z",
    "score": 22.76,
    "active": false
  }
]