[
  {
    "id": "da479af8-6827-4ec2-bca1-7c7273bf7d5f",
    "name": "Dave",
    "age": 66,
    "createdAt": "2025-07-17T10:11:46.623Z",
    "score": 76.75,
    "active": false
  },
  {
    "id": "8f1545c3-39e1-4902-90b6-534da101d9a0",
    "name": "Bob",
    "age": 59,
    "createdAt": "2025-07-17T10:11:46.634Z",
    "score": 6.38,
    "active": true
  },
  {
    "id": "84642c05-b5e6-499c-a809-2556f6d6084c",
    "name": "Frank",
    "age": 76,
    "createdAt": "2025-07-17T10:11:46.639Z",
    "score": 81.12,
    "active": true
  },
  {
    "id": "6c0a37df-6c55-4dd6-a102-3422653ec260",
    "name": "Frank",
    "age": 38,
    "createdAt": "2025-07-17T10:11:46.647Z",
    "score": 93.11,
    "active": false
  },
  {
    "id": "954e6428-f5e0-441c-9abe-b945fba60484",
    "name": "Grace",
    "age": 61,
    "createdAt": "2025-07-17T10:11:46.654Z",
    "score": 57.64,
    "active": false
  },
  {
    "id": "b78ebe35-127b-4315-9421-3719c8d453fa",
    "name": "Grace",
    "age": 51,
    "createdAt": "2025-07-17T10:11:46.656Z",
    "score": 94.3,
    "active": false
  },
  {
    "id": "c4bf9715-5e99-4383-82e1-6ff65c2d4074",
    "name": "Eve",
    "age": 46,
    "createdAt": "2025-07-17T10:11:46.658Z",
    "score": 92.78,
    "active": false
  },
  {
    "id": "9d41b13d-85af-47a8-9c05-0f484854de54",
    "name": "Carol",
    "age": 33,
    "createdAt": "2025-07-17T10:11:46.678Z",
    "score": 15.78,
    "active": false
  },
  {
    "id": "a7e3c735-0d34-4822-b02d-088af6f6b371",
    "name": "Frank",
    "age": 37,
    "createdAt": "2025-07-17T10:11:46.691Z",
    "score": 12.14,
    "active": false
  },
  {
    "id": "623a27db-8554-4b99-9665-4e7a2d31e724",
    "name": "Frank",
    "age": 26,
    "createdAt": "2025-07-17T10:11:46.695Z",
    "score": 28.05,
    "active": false
  }
]