[
  {
    "id": "fcdb1ec1-da58-46ad-9895-2391ee8c36e6",
    "name": "Bob",
    "age": 68,
    "createdAt": "2025-07-15T06:41:46.776Z",
    "score": 88.85,
    "active": false
  },
  {
    "id": "087465da-3251-4441-b151-47d9627ab762",
    "name": "Dave",
    "age": 75,
    "createdAt": "2025-07-15T06:41:46.804Z",
    "score": 50.43,
    "active": false
  },
  {
    "id": "305a1024-c7dc-40fd-9939-c5ca210f6c39",
    "name": "Grace",
    "age": 25,
    "createdAt": "2025-07-15T06:41:46.815Z",
    "score": 92.88,
    "active": false
  },
  {
    "id": "c757cd4f-b7c5-4087-8568-2362be18c5f9",
    "name": "Carol",
    "age": 33,
    "createdAt": "2025-07-15T06:41:46.842Z",
    "score": 86.56,
    "active": false
  },
  {
    "id": "9ddbda10-2405-4ba7-b86f-bf40d8b58d35",
    "name": "Eve",
    "age": 26,
    "createdAt": "2025-07-15T06:41:46.844Z",
    "score": 70.34,
    "active": true
  },
  {
    "id": "242e8a6f-e7ff-4723-80bb-93a5ec2e6627",
    "name": "Carol",
    "age": 50,
    "createdAt": "2025-07-15T06:41:46.860Z",
    "score": 75.74,
    "active": true
  },
  {
    "id": "6503d7e4-1c4e-425b-ba7e-7968849c7a4d",
    "name": "Eve",
    "age": 53,
    "createdAt": "2025-07-15T06:41:46.931Z",
    "score": 38.66,
    "active": false
  },
  {
    "id": "281f821b-dedb-428d-8950-962df35f2d62",
    "name": "Alice",
    "age": 27,
    "createdAt": "2025-07-15T06:41:46.941Z",
    "score": 97.82,
    "active": false
  },
  {
    "id": "2b91b287-f4d5-42e3-bf60-f85a7d8d2e75",
    "name": "Frank",
    "age": 63,
    "createdAt": "2025-07-15T06:41:46.991Z",
    "score": 47.54,
    "active": false
  },
  {
    "id": "2fe0c1bf-6334-48b2-b649-fffa0289e7e1",
    "name": "Dave",
    "age": 68,
    "createdAt": "2025-07-15T06:41:47.136Z",
    "score": 55.72,
    "active": false
  }
]