[
  {
    "id": "1d20284d-3715-4d22-95d0-17f228a2a1a9",
    "name": "Grace",
    "age": 26,
    "createdAt": "2025-07-16T11:56:48.287Z",
    "score": 47.02,
    "active": true
  },
  {
    "id": "496e7153-7f42-4d39-bd30-675da26c314b",
    "name": "Carol",
    "age": 40,
    "createdAt": "2025-07-16T11:56:48.298Z",
    "score": 21.9,
    "active": true
  },
  {
    "id": "09cde358-9068-4e2c-a834-65f0b89b83f8",
    "name": "Frank",
    "age": 30,
    "createdAt": "2025-07-16T11:56:48.302Z",
    "score": 61.56,
    "active": false
  },
  {
    "id": "f04f7a34-1e97-4142-885f-a0e9b35dc9eb",
    "name": "Frank",
    "age": 58,
    "createdAt": "2025-07-16T11:56:48.305Z",
    "score": 52.55,
    "active": false
  },
  {
    "id": "fa02d5c5-0268-4ee8-9fb2-2a9242426274",
    "name": "Alice",
    "age": 19,
    "createdAt": "2025-07-16T11:56:48.306Z",
    "score": 53.62,
    "active": false
  },
  {
    "id": "2a8a46ec-a2eb-422c-aeb9-1c5feb68d704",
    "name": "Grace",
    "age": 47,
    "createdAt": "2025-07-16T11:56:48.307Z",
    "score": 47.96,
    "active": true
  },
  {
    "id": "7f1e3b3b-efa0-4483-b06c-59fc85479578",
    "name": "Grace",
    "age": 34,
    "createdAt": "2025-07-16T11:56:48.309Z",
    "score": 18.92,
    "active": false
  },
  {
    "id": "2a1c832f-557b-4cc0-847f-969130f6ade3",
    "name": "Alice",
    "age": 59,
    "createdAt": "2025-07-16T11:56:48.312Z",
    "score": 15.31,
    "active": true
  },
  {
    "id": "454d85b8-4e0f-4646-9f14-3f576a053a66",
    "name": "Frank",
    "age": 47,
    "createdAt": "2025-07-16T11:56:48.319Z",
    "score": 77.32,
    "active": true
  },
  {
    "id": "7520f678-212f-4772-b10f-e84f8e321515",
    "name": "Alice",
    "age": 37,
    "createdAt": "2025-07-16T11:56:48.322Z",
    "score": 26.14,
    "active": false
  }
]