[
  {
    "id": "22ddac64-984b-4c9a-9ed5-d9804bc9539c",
    "name": "Grace",
    "age": 45,
    "createdAt": "2025-08-02T08:56:45.954Z",
    "score": 13.42,
    "active": true
  },
  {
    "id": "f64886b4-1c83-45be-9df5-d789242a26bf",
    "name": "Dave",
    "age": 24,
    "createdAt": "2025-08-02T08:56:45.982Z",
    "score": 60.1,
    "active": true
  },
  {
    "id": "75d76e91-181a-4baf-aaec-60058e61f743",
    "name": "Eve",
    "age": 69,
    "createdAt": "2025-08-02T08:56:45.984Z",
    "score": 66.46,
    "active": true
  },
  {
    "id": "8e71a16d-90e7-4d62-9908-d7c53ef6a03a",
    "name": "Grace",
    "age": 34,
    "createdAt": "2025-08-02T08:56:45.988Z",
    "score": 10.68,
    "active": true
  },
  {
    "id": "2b9b4e39-bd5b-41fc-b0cf-beccee662528",
    "name": "Grace",
    "age": 67,
    "createdAt": "2025-08-02T08:56:46.010Z",
    "score": 94.43,
    "active": true
  },
  {
    "id": "1c147299-17d3-4fb8-9d41-1332a6c39b4f",
    "name": "Grace",
    "age": 28,
    "createdAt": "2025-08-02T08:56:46.013Z",
    "score": 94.63,
    "active": false
  },
  {
    "id": "4ba0018b-a4b2-4953-ae1b-efa3397bae45",
    "name": "Bob",
    "age": 20,
    "createdAt": "2025-08-02T08:56:46.018Z",
    "score": 29.1,
    "active": true
  },
  {
    "id": "ad1fb4bd-fdb7-4fcf-9c56-ff72a1f9c841",
    "name": "Grace",
    "age": 54,
    "createdAt": "2025-08-02T08:56:46.019Z",
    "score": 71.35,
    "active": false
  },
  {
    "id": "01ba397d-a443-4e40-a2f4-c99a4f5aaa6e",
    "name": "Frank",
    "age": 69,
    "createdAt": "2025-08-02T08:56:46.021Z",
    "score": 35.39,
    "active": false
  },
  {
    "id": "2eca8b38-e583-4e4d-ac87-2fcabd31754d",
    "name": "Carol",
    "age": 59,
    "createdAt": "2025-08-02T08:56:46.022Z",
    "score": 29.67,
    "active": true
  }
]