[
  {
    "id": "4c4b4176-b66b-4245-ba8b-3e78a75a5d19",
    "name": "Bob",
    "age": 66,
    "createdAt": "2025-07-12T17:56:45.819Z",
    "score": 70.4,
    "active": true
  },
  {
    "id": "661b86d2-f607-4156-81d2-8dff89a34172",
    "name": "Grace",
    "age": 58,
    "createdAt": "2025-07-12T17:56:45.834Z",
    "score": 28.4,
    "active": false
  },
  {
    "id": "7e7675b4-b581-4f57-8108-c2aa9d7fe62a",
    "name": "Alice",
    "age": 68,
    "createdAt": "2025-07-12T17:56:45.835Z",
    "score": 60.4,
    "active": false
  },
  {
    "id": "de2e06bc-29e0-4353-a1b9-5b39b35e4c42",
    "name": "Frank",
    "age": 34,
    "createdAt": "2025-07-12T17:56:45.835Z",
    "score": 77.01,
    "active": false
  },
  {
    "id": "20935e16-9b2f-4d87-be02-71fefafd2626",
    "name": "Bob",
    "age": 66,
    "createdAt": "2025-07-12T17:56:45.836Z",
    "score": 77.08,
    "active": false
  },
  {
    "id": "d7193333-706b-44a3-8408-a2620a8f15ae",
    "name": "Alice",
    "age": 68,
    "createdAt": "2025-07-12T17:56:45.836Z",
    "score": 88.31,
    "active": false
  },
  {
    "id": "8020f349-ea7b-4cd2-b3aa-300f1fbeb71d",
    "name": "Eve",
    "age": 41,
    "createdAt": "2025-07-12T17:56:45.836Z",
    "score": 73.76,
    "active": false
  },
  {
    "id": "a3fc999d-7d62-4756-a779-0211df0d49ed",
    "name": "Bob",
    "age": 50,
    "createdAt": "2025-07-12T17:56:45.837Z",
    "score": 53.98,
    "active": false
  },
  {
    "id": "2d6f3365-8503-4428-b3b7-e52314cb179b",
    "name": "Alice",
    "age": 68,
    "createdAt": "2025-07-12T17:56:45.837Z",
    "score": 41.81,
    "active": false
  },
  {
    "id": "cd8cf100-ca08-4a4e-85a3-efce6735a494",
    "name": "Frank",
    "age": 76,
    "createdAt": "2025-07-12T17:56:45.837Z",
    "score": 89.79,
    "active": true
  }
]