[
  {
    "id": "7d0c3fc5-aed7-4392-90bf-dbaaa65539f4",
    "name": "Frank",
    "age": 53,
    "createdAt": "2025-07-29T05:26:46.152Z",
    "score": 49.91,
    "active": false
  },
  {
    "id": "5d2cb1fc-49f1-4c7f-89c0-be8a069c5df4",
    "name": "Carol",
    "age": 43,
    "createdAt": "2025-07-29T05:26:46.153Z",
    "score": 86.51,
    "active": false
  },
  {
    "id": "249a0646-23cb-4b67-bde3-26907fb89704",
    "name": "Frank",
    "age": 43,
    "createdAt": "2025-07-29T05:26:46.156Z",
    "score": 11.79,
    "active": false
  },
  {
    "id": "136c7ac2-fe5a-48fb-962a-2f8f98eb5078",
    "name": "Eve",
    "age": 62,
    "createdAt": "2025-07-29T05:26:46.158Z",
    "score": 49.74,
    "active": true
  },
  {
    "id": "d9eb53a9-2002-431e-8d56-98142a2e85b6",
    "name": "Grace",
    "age": 37,
    "createdAt": "2025-07-29T05:26:46.161Z",
    "score": 68.69,
    "active": true
  },
  {
    "id": "f0ac036f-4125-4d11-b566-4ae6ddaef662",
    "name": "Carol",
    "age": 26,
    "createdAt": "2025-07-29T05:26:46.170Z",
    "score": 1.94,
    "active": false
  },
  {
    "id": "5ce9fac1-450f-486f-aa05-a8a77d111f7c",
    "name": "Carol",
    "age": 50,
    "createdAt": "2025-07-29T05:26:46.175Z",
    "score": 36.72,
    "active": false
  },
  {
    "id": "5e303c09-2afd-41b9-940d-0ef3546a5a7c",
    "name": "Frank",
    "age": 51,
    "createdAt": "2025-07-29T05:26:46.178Z",
    "score": 52.42,
    "active": true
  },
  {
    "id": "3684bc13-558d-4075-9b6e-695c591802f2",
    "name": "Carol",
    "age": 51,
    "createdAt": "2025-07-29T05:26:46.185Z",
    "score": 19.29,
    "active": false
  },
  {
    "id": "9a82e57c-95aa-43b0-9df5-4e67eee8cc44",
    "name": "Dave",
    "age": 28,
    "createdAt": "2025-07-29T05:26:46.188Z",
    "score": 87.48,
    "active": false
  }
]