[
  {
    "id": "98f79c34-0303-4abc-8ef7-b5f62c42bf99",
    "name": "Carol",
    "age": 31,
    "createdAt": "2025-08-03T16:26:46.696Z",
    "score": 8.27,
    "active": true
  },
  {
    "id": "3cc57763-240b-4b4e-b8be-6f9ef9018a72",
    "name": "Eve",
    "age": 38,
    "createdAt": "2025-08-03T16:26:46.702Z",
    "score": 1.04,
    "active": true
  },
  {
    "id": "9ea495d0-ecca-4139-8c8b-d17114ad0f78",
    "name": "Frank",
    "age": 70,
    "createdAt": "2025-08-03T16:26:46.704Z",
    "score": 97.92,
    "active": true
  },
  {
    "id": "f1de8eef-ce38-4fe9-ad14-05ceef8644f6",
    "name": "Alice",
    "age": 36,
    "createdAt": "2025-08-03T16:26:46.710Z",
    "score": 2.66,
    "active": true
  },
  {
    "id": "195aa211-bfe4-4454-b148-c3d17cb4c5ab",
    "name": "Eve",
    "age": 34,
    "createdAt": "2025-08-03T16:26:46.739Z",
    "score": 34.14,
    "active": true
  },
  {
    "id": "c32311f5-5fab-4d98-a4ed-2d764c47bbed",
    "name": "Carol",
    "age": 44,
    "createdAt": "2025-08-03T16:26:46.745Z",
    "score": 9.62,
    "active": true
  },
  {
    "id": "dcde28a5-b632-4b48-be63-1ed28ee9c955",
    "name": "Eve",
    "age": 31,
    "createdAt": "2025-08-03T16:26:46.767Z",
    "score": 93.59,
    "active": true
  },
  {
    "id": "97d45aba-3d05-488d-a4d6-846ae54d4244",
    "name": "Dave",
    "age": 33,
    "createdAt": "2025-08-03T16:26:46.774Z",
    "score": 24.95,
    "active": false
  },
  {
    "id": "a17a251f-5f23-4a0b-a2dd-2c116b62e6a9",
    "name": "Alice",
    "age": 42,
    "createdAt": "2025-08-03T16:26:46.780Z",
    "score": 20.6,
    "active": true
  },
  {
    "id": "79ddcb41-d804-4001-931d-c9386eb52e7c",
    "name": "Grace",
    "age": 67,
    "createdAt": "2025-08-03T16:26:46.782Z",
    "score": 77.61,
    "active": true
  }
]