[
  {
    "id": "810b5b52-0052-4734-baa9-daab00636496",
    "name": "Grace",
    "age": 55,
    "createdAt": "2025-07-17T04:41:48.783Z",
    "score": 28.22,
    "active": false
  },
  {
    "id": "546c4c22-3e7e-4260-85e2-69581f3d8ea2",
    "name": "Carol",
    "age": 56,
    "createdAt": "2025-07-17T04:41:48.889Z",
    "score": 54.47,
    "active": false
  },
  {
    "id": "28444362-5ae7-4f06-89ef-35e03222bcd4",
    "name": "Bob",
    "age": 53,
    "createdAt": "2025-07-17T04:41:48.897Z",
    "score": 13.26,
    "active": true
  },
  {
    "id": "80faa455-4351-4969-b1e8-85cc1ae8914c",
    "name": "Eve",
    "age": 47,
    "createdAt": "2025-07-17T04:41:48.927Z",
    "score": 16.04,
    "active": false
  },
  {
    "id": "d875ceee-948e-4049-a8cd-5f35fbe38ca0",
    "name": "Frank",
    "age": 19,
    "createdAt": "2025-07-17T04:41:49.002Z",
    "score": 99.3,
    "active": true
  },
  {
    "id": "0d8da346-374d-44cd-b46d-1710c1a5c5e3",
    "name": "Dave",
    "age": 51,
    "createdAt": "2025-07-17T04:41:49.011Z",
    "score": 20.57,
    "active": false
  },
  {
    "id": "479ac075-1c13-4b62-93ad-bd44983b6c30",
    "name": "Eve",
    "age": 48,
    "createdAt": "2025-07-17T04:41:49.028Z",
    "score": 72.36,
    "active": true
  },
  {
    "id": "8e1cfc2b-8d21-4f2f-a41b-930cf702d16a",
    "name": "Grace",
    "age": 72,
    "createdAt": "2025-07-17T04:41:49.112Z",
    "score": 58.04,
    "active": true
  },
  {
    "id": "e49438e6-a8d6-49c9-9779-7f00c99de469",
    "name": "Bob",
    "age": 45,
    "createdAt": "2025-07-17T04:41:49.116Z",
    "score": 46.59,
    "active": true
  },
  {
    "id": "28a795b5-c1e8-4ee9-a067-943ee70b95ff",
    "name": "Eve",
    "age": 64,
    "createdAt": "2025-07-17T04:41:49.133Z",
    "score": 36.87,
    "active": false
  }
]