[
  {
    "id": "f18412e4-d94f-46c6-9ba0-95b51e521e04",
    "name": "Alice",
    "age": 42,
    "createdAt": "2025-07-18T07:26:48.158Z",
    "score": 77.13,
    "active": true
  },
  {
    "id": "bf69a4ed-586a-480d-8c63-506f95594601",
    "name": "Alice",
    "age": 34,
    "createdAt": "2025-07-18T07:26:48.164Z",
    "score": 46.53,
    "active": false
  },
  {
    "id": "b9cdbfb5-6911-4bb5-b53a-a68ae409ef77",
    "name": "Frank",
    "age": 56,
    "createdAt": "2025-07-18T07:26:48.165Z",
    "score": 11.05,
    "active": false
  },
  {
    "id": "31fa70d3-cf37-4689-98ef-e644bce84285",
    "name": "Frank",
    "age": 63,
    "createdAt": "2025-07-18T07:26:48.166Z",
    "score": 50.17,
    "active": false
  },
  {
    "id": "ba997850-2ffb-48c2-ae7f-4c11937335eb",
    "name": "Bob",
    "age": 44,
    "createdAt": "2025-07-18T07:26:48.167Z",
    "score": 48.14,
    "active": false
  },
  {
    "id": "3c448f14-a56e-48a7-a7be-d59a6d1649c5",
    "name": "Bob",
    "age": 25,
    "createdAt": "2025-07-18T07:26:48.175Z",
    "score": 1.75,
    "active": false
  },
  {
    "id": "3b126196-6578-44bd-a678-561d5b67f963",
    "name": "Carol",
    "age": 47,
    "createdAt": "2025-07-18T07:26:48.175Z",
    "score": 18.41,
    "active": true
  },
  {
    "id": "f43f8686-0a76-4d0f-ae1d-b4044be6ac91",
    "name": "Dave",
    "age": 54,
    "createdAt": "2025-07-18T07:26:48.176Z",
    "score": 19.88,
    "active": true
  },
  {
    "id": "a3c3c285-997b-407b-92ee-bbdfd12eb00e",
    "name": "Frank",
    "age": 26,
    "createdAt": "2025-07-18T07:26:48.183Z",
    "score": 82.03,
    "active": true
  },
  {
    "id": "2d09c928-eeb0-4100-a4c6-f7deff21509b",
    "name": "Carol",
    "age": 33,
    "createdAt": "2025-07-18T07:26:48.189Z",
    "score": 66.34,
    "active": true
  }
]