[
  {
    "id": "ea5281d1-7c6c-4ee3-bf38-fca701b51527",
    "name": "Grace",
    "age": 44,
    "createdAt": "2025-07-24T00:26:45.914Z",
    "score": 49.23,
    "active": false
  },
  {
    "id": "37d03383-5231-4c37-9eca-acaf76ede033",
    "name": "Dave",
    "age": 69,
    "createdAt": "2025-07-24T00:26:45.922Z",
    "score": 66.17,
    "active": false
  },
  {
    "id": "4627e9b0-9aa9-4c0a-8e37-f499b924d9aa",
    "name": "Frank",
    "age": 65,
    "createdAt": "2025-07-24T00:26:45.923Z",
    "score": 94.74,
    "active": false
  },
  {
    "id": "8d5fe455-9223-473d-94bf-30c6dc59515e",
    "name": "Frank",
    "age": 64,
    "createdAt": "2025-07-24T00:26:45.924Z",
    "score": 88.95,
    "active": true
  },
  {
    "id": "86fe3348-cbe9-4c14-b51e-c5da534796f5",
    "name": "Dave",
    "age": 51,
    "createdAt": "2025-07-24T00:26:45.924Z",
    "score": 7.36,
    "active": true
  },
  {
    "id": "64308ce0-ef28-4067-a418-ec7c329edd34",
    "name": "Eve",
    "age": 61,
    "createdAt": "2025-07-24T00:26:45.924Z",
    "score": 47.45,
    "active": true
  },
  {
    "id": "45105505-6052-4ba3-ad12-056bea1635f9",
    "name": "Carol",
    "age": 27,
    "createdAt": "2025-07-24T00:26:45.925Z",
    "score": 86.85,
    "active": true
  },
  {
    "id": "b91519b7-6340-485d-a661-90ba6293b842",
    "name": "Dave",
    "age": 22,
    "createdAt": "2025-07-24T00:26:45.926Z",
    "score": 63.29,
    "active": false
  },
  {
    "id": "e37d00bf-2ede-47cd-9bd5-e8c5c8ea8f04",
    "name": "Eve",
    "age": 29,
    "createdAt": "2025-07-24T00:26:45.927Z",
    "score": 64.6,
    "active": true
  },
  {
    "id": "61313c94-f3a1-4dcf-968c-12079bcf69eb",
    "name": "Frank",
    "age": 68,
    "createdAt": "2025-07-24T00:26:45.927Z",
    "score": 0.89,
    "active": true
  }
]