[
  {
    "id": "0e1f00a7-f015-4ce6-ac35-a69dd8162634",
    "name": "Carol",
    "age": 32,
    "createdAt": "2025-07-23T12:41:47.766Z",
    "score": 79.05,
    "active": true
  },
  {
    "id": "b308a7f1-3bb7-4438-a830-20add5c68b21",
    "name": "Bob",
    "age": 58,
    "createdAt": "2025-07-23T12:41:47.766Z",
    "score": 24.28,
    "active": false
  },
  {
    "id": "96ea6b9d-0a5c-4fce-865f-5d6aa1df9e8f",
    "name": "Frank",
    "age": 41,
    "createdAt": "2025-07-23T12:41:47.767Z",
    "score": 86.19,
    "active": true
  },
  {
    "id": "e7776147-f274-427f-8feb-03ca451fa75e",
    "name": "Bob",
    "age": 67,
    "createdAt": "2025-07-23T12:41:47.767Z",
    "score": 33.73,
    "active": false
  },
  {
    "id": "5331ce51-026a-4c48-83ab-52adcc4caeb1",
    "name": "Grace",
    "age": 75,
    "createdAt": "2025-07-23T12:41:47.767Z",
    "score": 70.33,
    "active": true
  },
  {
    "id": "6c53d601-434b-456a-b706-ec71f8f4dc4f",
    "name": "Bob",
    "age": 44,
    "createdAt": "2025-07-23T12:41:47.768Z",
    "score": 35.67,
    "active": true
  },
  {
    "id": "13c7d7a6-7908-4535-adc1-4605eaa08b25",
    "name": "Carol",
    "age": 72,
    "createdAt": "2025-07-23T12:41:47.768Z",
    "score": 12.01,
    "active": true
  },
  {
    "id": "566a7c8c-22fb-4753-a505-b11b55313b6d",
    "name": "Carol",
    "age": 37,
    "createdAt": "2025-07-23T12:41:47.768Z",
    "score": 50.68,
    "active": false
  },
  {
    "id": "d2bdb466-d405-40dd-9d03-d81a7450e374",
    "name": "Frank",
    "age": 68,
    "createdAt": "2025-07-23T12:41:47.768Z",
    "score": 99.58,
    "active": false
  },
  {
    "id": "6e82e96b-98dc-4635-90c0-5c5526a5a68f",
    "name": "Eve",
    "age": 56,
    "createdAt": "2025-07-23T12:41:47.769Z",
    "score": 47.72,
    "active": false
  }
]