[
  {
    "id": "02be9596-bd06-4ac5-a95f-7199a871e4f4",
    "name": "Alice",
    "age": 32,
    "createdAt": "2025-07-23T23:26:46.359Z",
    "score": 75.07,
    "active": true
  },
  {
    "id": "fe7aa774-b855-484a-8f6c-9a758dc8840d",
    "name": "Carol",
    "age": 18,
    "createdAt": "2025-07-23T23:26:46.392Z",
    "score": 98.22,
    "active": false
  },
  {
    "id": "53d06d26-e19c-4e3b-9719-50726a928262",
    "name": "Eve",
    "age": 55,
    "createdAt": "2025-07-23T23:26:46.409Z",
    "score": 91.25,
    "active": false
  },
  {
    "id": "578c80c4-dc03-45f5-9107-043dc29b38d3",
    "name": "Frank",
    "age": 54,
    "createdAt": "2025-07-23T23:26:46.418Z",
    "score": 31.6,
    "active": true
  },
  {
    "id": "c9a0bdbb-4ecf-458e-b75e-f91bf0f5113a",
    "name": "Dave",
    "age": 75,
    "createdAt": "2025-07-23T23:26:46.423Z",
    "score": 91.8,
    "active": true
  },
  {
    "id": "6c1b6de6-609a-455f-829a-6e2559954c45",
    "name": "Carol",
    "age": 64,
    "createdAt": "2025-07-23T23:26:46.430Z",
    "score": 46.27,
    "active": true
  },
  {
    "id": "05f1bfd2-370e-4c28-a226-d71adeffafcb",
    "name": "Bob",
    "age": 62,
    "createdAt": "2025-07-23T23:26:46.438Z",
    "score": 24.06,
    "active": false
  },
  {
    "id": "445fa576-8986-48c0-b54c-d866812a67fa",
    "name": "Eve",
    "age": 20,
    "createdAt": "2025-07-23T23:26:46.452Z",
    "score": 34.59,
    "active": true
  },
  {
    "id": "c2bd663d-1528-485c-bb3f-e69c8a9542a1",
    "name": "Dave",
    "age": 65,
    "createdAt": "2025-07-23T23:26:46.458Z",
    "score": 5.86,
    "active": false
  },
  {
    "id": "65504e9d-947f-4b26-bb0c-70577da16a03",
    "name": "Frank",
    "age": 70,
    "createdAt": "2025-07-23T23:26:46.462Z",
    "score": 48.21,
    "active": false
  }
]