[
  {
    "id": "166446ff-5f41-416f-a145-69982261b819",
    "name": "Dave",
    "age": 38,
    "createdAt": "2025-07-30T19:26:46.418Z",
    "score": 29.04,
    "active": false
  },
  {
    "id": "5abe6f05-3057-40c3-b340-167685c1bcd3",
    "name": "Dave",
    "age": 37,
    "createdAt": "2025-07-30T19:26:46.429Z",
    "score": 44.13,
    "active": false
  },
  {
    "id": "07cbc2c1-ebf8-4bbb-90ef-41a4d0bbc109",
    "name": "Eve",
    "age": 43,
    "createdAt": "2025-07-30T19:26:46.437Z",
    "score": 98.15,
    "active": true
  },
  {
    "id": "c95b71e3-6b67-460e-b3e3-19805ddeb2f3",
    "name": "Eve",
    "age": 54,
    "createdAt": "2025-07-30T19:26:46.439Z",
    "score": 17.2,
    "active": true
  },
  {
    "id": "e684cc3e-35ce-4e2f-b094-1a6cac0cd686",
    "name": "Bob",
    "age": 72,
    "createdAt": "2025-07-30T19:26:46.450Z",
    "score": 90.43,
    "active": false
  },
  {
    "id": "a4340899-369c-4583-b1a6-9b916c5abec3",
    "name": "Eve",
    "age": 24,
    "createdAt": "2025-07-30T19:26:46.455Z",
    "score": 62.11,
    "active": true
  },
  {
    "id": "1012b212-1cba-4db2-aad0-a60a42629ef0",
    "name": "Carol",
    "age": 58,
    "createdAt": "2025-07-30T19:26:46.457Z",
    "score": 56.78,
    "active": false
  },
  {
    "id": "9ca52f52-6dbb-4614-b151-0ba922d2fe38",
    "name": "Dave",
    "age": 56,
    "createdAt": "2025-07-30T19:26:46.459Z",
    "score": 26.86,
    "active": true
  },
  {
    "id": "dcfa081f-652f-4bcf-9ccd-c35dbe8f277e",
    "name": "Eve",
    "age": 38,
    "createdAt": "2025-07-30T19:26:46.460Z",
    "score": 16.55,
    "active": false
  },
  {
    "id": "235ab8e5-47e3-4737-87eb-950cbe38ab92",
    "name": "Alice",
    "age": 30,
    "createdAt": "2025-07-30T19:26:46.462Z",
    "score": 92.7,
    "active": true
  }
]