[
  {
    "id": "3509fa27-dd0e-4d99-a2a5-83564e3d6ee0",
    "name": "Grace",
    "age": 59,
    "createdAt": "2025-07-20T23:41:47.891Z",
    "score": 1.25,
    "active": true
  },
  {
    "id": "7ca17b79-e5a5-41f2-b87c-7f1081fb4efb",
    "name": "Grace",
    "age": 25,
    "createdAt": "2025-07-20T23:41:47.904Z",
    "score": 24.81,
    "active": true
  },
  {
    "id": "d6d2b8ba-8b62-45c0-b210-01ac342be635",
    "name": "Frank",
    "age": 73,
    "createdAt": "2025-07-20T23:41:47.904Z",
    "score": 80.14,
    "active": true
  },
  {
    "id": "374008d5-e683-43ff-80f3-2ab5c21c9efa",
    "name": "Carol",
    "age": 29,
    "createdAt": "2025-07-20T23:41:47.907Z",
    "score": 91.98,
    "active": true
  },
  {
    "id": "c2eaa3f0-522e-4638-8d30-774d3a96d461",
    "name": "Grace",
    "age": 45,
    "createdAt": "2025-07-20T23:41:47.910Z",
    "score": 58.83,
    "active": true
  },
  {
    "id": "177a69bb-fb99-420b-9e67-aabda62f4e7f",
    "name": "Alice",
    "age": 54,
    "createdAt": "2025-07-20T23:41:47.911Z",
    "score": 33.28,
    "active": false
  },
  {
    "id": "a77e1a7b-279d-4cef-a8b5-de5eea4559d1",
    "name": "Carol",
    "age": 65,
    "createdAt": "2025-07-20T23:41:47.912Z",
    "score": 93.52,
    "active": false
  },
  {
    "id": "f2967b69-19be-4c05-b216-fe96836f12f0",
    "name": "Bob",
    "age": 76,
    "createdAt": "2025-07-20T23:41:47.912Z",
    "score": 30.01,
    "active": false
  },
  {
    "id": "da8b2249-1da9-4ad5-bcb6-1886bbcb8821",
    "name": "Frank",
    "age": 67,
    "createdAt": "2025-07-20T23:41:47.913Z",
    "score": 12.39,
    "active": true
  },
  {
    "id": "1d26848f-e3ec-47eb-813f-575ff78a2630",
    "name": "Carol",
    "age": 18,
    "createdAt": "2025-07-20T23:41:47.913Z",
    "score": 31.89,
    "active": false
  }
]