[
  {
    "id": "de3fe842-cef5-44b4-86aa-09d1f18abe41",
    "name": "Eve",
    "age": 19,
    "createdAt": "2025-08-01T15:26:48.146Z",
    "score": 73.25,
    "active": false
  },
  {
    "id": "6da994fb-e211-46e1-8645-b3551f1b5a39",
    "name": "Carol",
    "age": 39,
    "createdAt": "2025-08-01T15:26:48.159Z",
    "score": 42.58,
    "active": false
  },
  {
    "id": "f17d0879-b3a2-46ed-ab63-9572cbb15df8",
    "name": "Dave",
    "age": 28,
    "createdAt": "2025-08-01T15:26:48.161Z",
    "score": 65.65,
    "active": false
  },
  {
    "id": "d2d6dbf9-962b-4e23-9119-17903a77d43c",
    "name": "Dave",
    "age": 39,
    "createdAt": "2025-08-01T15:26:48.161Z",
    "score": 94.57,
    "active": true
  },
  {
    "id": "8893bde7-b4be-4843-921d-9b02331dffce",
    "name": "Eve",
    "age": 65,
    "createdAt": "2025-08-01T15:26:48.162Z",
    "score": 66.45,
    "active": false
  },
  {
    "id": "15c17343-fdf7-4106-ae7c-a959db18964c",
    "name": "Carol",
    "age": 47,
    "createdAt": "2025-08-01T15:26:48.163Z",
    "score": 28.29,
    "active": true
  },
  {
    "id": "49914117-d198-4708-999d-bf23570bae84",
    "name": "Frank",
    "age": 23,
    "createdAt": "2025-08-01T15:26:48.163Z",
    "score": 28.23,
    "active": true
  },
  {
    "id": "8edeb3e0-03ea-456f-ac78-41bc318a3413",
    "name": "Frank",
    "age": 61,
    "createdAt": "2025-08-01T15:26:48.164Z",
    "score": 50.69,
    "active": false
  },
  {
    "id": "20740cd2-0727-409c-b97b-d1031e274075",
    "name": "Grace",
    "age": 45,
    "createdAt": "2025-08-01T15:26:48.166Z",
    "score": 8.33,
    "active": false
  },
  {
    "id": "25de6232-2a87-4161-bbfa-de139949a8fb",
    "name": "Frank",
    "age": 67,
    "createdAt": "2025-08-01T15:26:48.167Z",
    "score": 45.78,
    "active": false
  }
]