[
  {
    "id": "90421d40-d195-4b63-843d-dd96a8ccbb51",
    "name": "Grace",
    "age": 58,
    "createdAt": "2025-07-25T12:11:47.861Z",
    "score": 40.53,
    "active": true
  },
  {
    "id": "e3ceb4b3-6f45-4e88-9148-e6205bbcbc00",
    "name": "Eve",
    "age": 63,
    "createdAt": "2025-07-25T12:11:47.863Z",
    "score": 57.45,
    "active": true
  },
  {
    "id": "b47827df-c5bf-48b5-a6b7-96fb80b9fe9a",
    "name": "Eve",
    "age": 72,
    "createdAt": "2025-07-25T12:11:47.864Z",
    "score": 53,
    "active": true
  },
  {
    "id": "c9a8a0de-5b46-491c-887e-ddc17f9f865c",
    "name": "Grace",
    "age": 22,
    "createdAt": "2025-07-25T12:11:47.867Z",
    "score": 69.41,
    "active": true
  },
  {
    "id": "1727355a-3552-4f1f-aba6-10fa31aa4e08",
    "name": "Eve",
    "age": 48,
    "createdAt": "2025-07-25T12:11:47.868Z",
    "score": 40.23,
    "active": true
  },
  {
    "id": "9a807b7f-2430-40d5-ac85-d0f099b2b913",
    "name": "Bob",
    "age": 33,
    "createdAt": "2025-07-25T12:11:47.869Z",
    "score": 63.15,
    "active": true
  },
  {
    "id": "3a9a139f-df4f-4415-a1d8-5c65529f42e4",
    "name": "Dave",
    "age": 26,
    "createdAt": "2025-07-25T12:11:47.870Z",
    "score": 69.18,
    "active": false
  },
  {
    "id": "b6efc0c5-26bb-4585-b712-4cc1dd60d637",
    "name": "Eve",
    "age": 35,
    "createdAt": "2025-07-25T12:11:47.872Z",
    "score": 42.02,
    "active": true
  },
  {
    "id": "d7311554-7368-404d-bbbf-6646695b0f4a",
    "name": "Frank",
    "age": 56,
    "createdAt": "2025-07-25T12:11:47.873Z",
    "score": 69.38,
    "active": false
  },
  {
    "id": "a935a893-11d2-4b1b-a1a2-1f50dbc618bc",
    "name": "Bob",
    "age": 23,
    "createdAt": "2025-07-25T12:11:47.875Z",
    "score": 19.52,
    "active": true
  }
]