[
  {
    "id": "078ebf59-1a2b-4c3d-be02-e891d9c13aea",
    "name": "Eve",
    "age": 61,
    "createdAt": "2025-07-19T23:41:48.487Z",
    "score": 75.95,
    "active": false
  },
  {
    "id": "fdd39ba7-9e3a-4f99-8a3a-9c30103d86fc",
    "name": "Bob",
    "age": 56,
    "createdAt": "2025-07-19T23:41:48.493Z",
    "score": 38.43,
    "active": true
  },
  {
    "id": "214deff3-9c23-4e30-b143-5a02464d92ea",
    "name": "Alice",
    "age": 25,
    "createdAt": "2025-07-19T23:41:48.502Z",
    "score": 64.57,
    "active": false
  },
  {
    "id": "b724a9d2-855a-4174-bc80-eb8a382c350d",
    "name": "Grace",
    "age": 21,
    "createdAt": "2025-07-19T23:41:48.507Z",
    "score": 74.32,
    "active": false
  },
  {
    "id": "dd8a9e17-ac12-4ccb-b264-10da41a0adbe",
    "name": "Eve",
    "age": 65,
    "createdAt": "2025-07-19T23:41:48.507Z",
    "score": 87.83,
    "active": false
  },
  {
    "id": "c1d28ac8-6238-4f71-a33d-4714a178291f",
    "name": "Frank",
    "age": 67,
    "createdAt": "2025-07-19T23:41:48.508Z",
    "score": 29.96,
    "active": true
  },
  {
    "id": "1bc500ca-498f-435d-b49d-3ed01b4bdae5",
    "name": "Bob",
    "age": 36,
    "createdAt": "2025-07-19T23:41:48.509Z",
    "score": 45.04,
    "active": true
  },
  {
    "id": "2fada5e7-3752-4b87-b15b-a264ea0e7e22",
    "name": "Frank",
    "age": 62,
    "createdAt": "2025-07-19T23:41:48.510Z",
    "score": 73.94,
    "active": false
  },
  {
    "id": "513e0233-18b4-481e-8f05-cc152e99845b",
    "name": "Frank",
    "age": 27,
    "createdAt": "2025-07-19T23:41:48.511Z",
    "score": 53.21,
    "active": true
  },
  {
    "id": "fd85df96-976c-4310-9a5f-e1ac05c15aa1",
    "name": "Grace",
    "age": 31,
    "createdAt": "2025-07-19T23:41:48.511Z",
    "score": 62.63,
    "active": false
  }
]