[
  {
    "id": "686ab6bd-287e-4e73-ad2a-d9e340fcae15",
    "name": "Frank",
    "age": 21,
    "createdAt": "2025-07-12T08:56:46.134Z",
    "score": 93.88,
    "active": true
  },
  {
    "id": "55639117-5a64-4768-b3c5-77c459f8380a",
    "name": "Alice",
    "age": 53,
    "createdAt": "2025-07-12T08:56:46.147Z",
    "score": 98.75,
    "active": false
  },
  {
    "id": "0843e383-21a0-4a49-b875-00b3c992cce9",
    "name": "Frank",
    "age": 20,
    "createdAt": "2025-07-12T08:56:46.148Z",
    "score": 65.33,
    "active": true
  },
  {
    "id": "56ddbb82-a12d-4d26-9e35-f0ef47b27f77",
    "name": "Dave",
    "age": 52,
    "createdAt": "2025-07-12T08:56:46.150Z",
    "score": 79.32,
    "active": true
  },
  {
    "id": "8c3f79c6-96ac-45ab-aa19-fe7845380927",
    "name": "Alice",
    "age": 65,
    "createdAt": "2025-07-12T08:56:46.152Z",
    "score": 83.21,
    "active": false
  },
  {
    "id": "36554098-328e-482c-8fa9-8221a39fc6f4",
    "name": "Bob",
    "age": 58,
    "createdAt": "2025-07-12T08:56:46.164Z",
    "score": 69.45,
    "active": true
  },
  {
    "id": "7ad778f9-d49a-4ea8-a3e6-bb55dd7890a5",
    "name": "Carol",
    "age": 67,
    "createdAt": "2025-07-12T08:56:46.165Z",
    "score": 97.33,
    "active": true
  },
  {
    "id": "662092b8-5b3c-44b1-a1d0-2c5b3ff134a6",
    "name": "Eve",
    "age": 52,
    "createdAt": "2025-07-12T08:56:46.168Z",
    "score": 41.01,
    "active": false
  },
  {
    "id": "df4b8173-3c74-4cf5-9a8d-a043f8cd7954",
    "name": "Dave",
    "age": 48,
    "createdAt": "2025-07-12T08:56:46.168Z",
    "score": 65.61,
    "active": true
  },
  {
    "id": "cf71241a-21e3-4fe5-a96f-91f6c948a8a6",
    "name": "Alice",
    "age": 76,
    "createdAt": "2025-07-12T08:56:46.170Z",
    "score": 92.86,
    "active": false
  }
]