[
  {
    "id": "83e9f683-64a4-459e-9b49-11fca7ca9039",
    "name": "Eve",
    "age": 69,
    "createdAt": "2025-08-02T21:56:47.576Z",
    "score": 20.17,
    "active": true
  },
  {
    "id": "1e468ec2-73fa-494d-b26e-7f88f1bf3b9a",
    "name": "Eve",
    "age": 44,
    "createdAt": "2025-08-02T21:56:47.578Z",
    "score": 6.18,
    "active": true
  },
  {
    "id": "5e84c9af-a8c0-46fa-9b9d-5942e49b9973",
    "name": "Dave",
    "age": 57,
    "createdAt": "2025-08-02T21:56:47.578Z",
    "score": 85.9,
    "active": false
  },
  {
    "id": "1d747f28-fa43-4d54-bfb7-68bcfd37ab9b",
    "name": "Carol",
    "age": 27,
    "createdAt": "2025-08-02T21:56:47.579Z",
    "score": 53.55,
    "active": false
  },
  {
    "id": "1c540f56-a2c5-4894-b057-3da500642141",
    "name": "Grace",
    "age": 65,
    "createdAt": "2025-08-02T21:56:47.579Z",
    "score": 13.71,
    "active": false
  },
  {
    "id": "03662e7d-d9b4-449c-9901-408e1b90b22e",
    "name": "Grace",
    "age": 72,
    "createdAt": "2025-08-02T21:56:47.580Z",
    "score": 98.77,
    "active": true
  },
  {
    "id": "764e8652-1d26-4088-a9ef-c804dacb035a",
    "name": "Grace",
    "age": 29,
    "createdAt": "2025-08-02T21:56:47.580Z",
    "score": 93.95,
    "active": true
  },
  {
    "id": "b477605e-19b7-4935-8759-d152d49d0700",
    "name": "Frank",
    "age": 50,
    "createdAt": "2025-08-02T21:56:47.580Z",
    "score": 23.98,
    "active": false
  },
  {
    "id": "0631d740-e762-457c-b2b2-327d002f132b",
    "name": "Grace",
    "age": 33,
    "createdAt": "2025-08-02T21:56:47.580Z",
    "score": 85.24,
    "active": true
  },
  {
    "id": "761c41c0-e1df-42c1-b771-11bcdca78d70",
    "name": "Grace",
    "age": 72,
    "createdAt": "2025-08-02T21:56:47.581Z",
    "score": 31.9,
    "active": true
  }
]